django_health_checkers-3.5.0.dist-info/DESCRIPTION.rst
django_health_checkers-3.5.0.dist-info/METADATA
django_health_checkers-3.5.0.dist-info/RECORD
django_health_checkers-3.5.0.dist-info/WHEEL
django_health_checkers-3.5.0.dist-info/metadata.json
django_health_checkers-3.5.0.dist-info/pbr.json
django_health_checkers-3.5.0.dist-info/top_level.txt
health_check/__init__.py
health_check/backends.py
health_check/exceptions.py
health_check/plugins.py
health_check/urls.py
health_check/views.py
health_check/cache/__init__.py
health_check/cache/apps.py
health_check/cache/backends.py
health_check/contrib/__init__.py
health_check/contrib/celery/__init__.py
health_check/contrib/celery/apps.py
health_check/contrib/celery/backends.py
health_check/contrib/celery/tasks.py
health_check/contrib/psutil/__init__.py
health_check/contrib/psutil/apps.py
health_check/contrib/psutil/backends.py
health_check/contrib/s3boto3_storage/__init__.py
health_check/contrib/s3boto3_storage/apps.py
health_check/contrib/s3boto3_storage/backends.py
health_check/contrib/s3boto_storage/__init__.py
health_check/contrib/s3boto_storage/apps.py
health_check/contrib/s3boto_storage/backends.py
health_check/db/__init__.py
health_check/db/apps.py
health_check/db/backends.py
health_check/db/models.py
health_check/db/migrations/0001_initial.py
health_check/db/migrations/__init__.py
health_check/storage/__init__.py
health_check/storage/apps.py
health_check/storage/backends.py
health_check/templates/health_check/index.html
