Metadata-Version: 2.0
Name: django-health-checkers
Version: 3.5.0
Summary: Run checks on services like databases, queue servers, celery processes, etc.
Home-page: https://github.com/KristianOellegaard/django-health-check
Author: Kristian Ollegaard
Author-email: kristian@oellegaard.com
License: BSD License
Keywords: django
